[
    {
      "id": 2,
      "name": "Meal Queue",
      "image": "https://i.imgur.com/CVZCOLm.gif",
      "description": "Recipe finder with a youtube modal that matches the recipe.",
      "tech": "SASS, APIs, HTML5, JavaScript ",
      "deployed": "https://axeliono.github.io/Meal-Queue/",
      "github": "https://github.com/axeliono/Meal-Queue"
    },
    {
      "id": 1,
      "name": "Hotel-Hotel",
      "image": "https://i.imgur.com/IR1SJIK.gif",
      "description": "A fictional boutique hotel with a store. ",
      "tech": "PWA, MERN stack, JSWT",
      "deployed": "https://dry-peak-24448.herokuapp.com/",
      "github": "https://github.com/axeliono/hotel-hotel"
    },
    {
      "id": 3,
      "name": "Diet Delivery",
      "image": "https://i.imgur.com/dXoK1wr.gif",
      "description": "An app for meal deliveries for people with chronic conditions.",
      "tech": "Node, Express, Handlebars, MySQL & Sequelize ORM, MVC, bcrypt.",
      "deployed": "https://diet-delivery.herokuapp.com/",
      "github": "https://github.com/MikeGShelby/diet-delivery"
    },
    {
      "id": 4,
      "name": "RegEx Tutorial",
      "image": "https://i.imgur.com/qpshDOt.gif",
      "description": "RegEx Tutorial",
      "tech": "Gist",
      "deployed": "RickySulli/regex-tutorial.md",
      "github": "RickySulli/regex-tutorial.md"
    },
    {
      "id": 5,
      "name": "Timed Coding Assessment",
      "image": "https://i.imgur.com/JC4gn3F.gif",
      "description": "simple front-end testing app",
      "tech": "HTML CSS and JavaScript",
      "deployed": "https://rickysulli.github.io/TimedCodingAssessment/",
      "github": "https://github.com/RickySulli/TimedCodingAssessment"
    },
    {
      "id": 6,
      "name": "Not Computers",
      "image": "https://i.imgur.com/D01jGxe.gif",
      "description": "Forever student of percussion.",
      "tech": "The Blues Specialists, Perfect Pants",
      "deployed": "https://perfectpants.bandcamp.com/",
      "github": ""
    }
]